rclonerc/__init__.py
rclonerc/client.py
rclonerc-0.0.1.dist-info/LICENSE.txt
rclonerc-0.0.1.dist-info/METADATA
rclonerc-0.0.1.dist-info/WHEEL
rclonerc-0.0.1.dist-info/top_level.txt
rclonerc-0.0.1.dist-info/RECORD
