Metadata-Version: 2.1
Name: rclonerc
Version: 0.0.1
Summary: RClone Remote Control Client for Python
Home-page: https://github.com/chenseanxy/rclonerc
Author: Xinyang Chen
Author-email: me@chenxy.tech
License: MIT
Platform: any
Classifier: Development Status :: 4 - Beta
Classifier: Programming Language :: Python
Requires-Python: >=3
License-File: LICENSE.txt
Requires-Dist: requests (<3.0,>=2)
Requires-Dist: importlib-metadata ; python_version < "3.8"
Provides-Extra: testing
Requires-Dist: setuptools ; extra == 'testing'
Requires-Dist: pytest ; extra == 'testing'
Requires-Dist: pytest-cov ; extra == 'testing'
